CHANGES.txt
LICENSE
MANIFEST.in
README.rst
distribute_setup.py
paver-minilib.zip
setup.py
Paved.egg-info/PKG-INFO
Paved.egg-info/SOURCES.txt
Paved.egg-info/dependency_links.txt
Paved.egg-info/not-zip-safe
Paved.egg-info/requires.txt
Paved.egg-info/top_level.txt
docs/Makefile
docs/api.paved.dist.rst
docs/api.paved.django.rst
docs/api.paved.docs.rst
docs/api.paved.pkg.rst
docs/api.paved.pycheck.rst
docs/api.paved.rst
docs/api.paved.util.rst
docs/api.rst
docs/conf.py
docs/index.rst
docs/quickstart.rst
docs/readme.rst
paved/__init__.py
paved/dist.py
paved/django.py
paved/docs.py
paved/paved.py
paved/pkg.py
paved/pycheck.py
paved/s3.py
paved/util.py