Metadata-Version: 1.1
Name: Paved
Version: 0.5.1
Summary: Common tasks for Paver-based projects.
Home-page: https://github.com/eykd/paved
Author: David Eyk
Author-email: eykd@eykd.net
License: BSD
Download-URL: http://pypi.python.org/pypi/Paved/
Platform: UNKNOWN
Classifier: Development Status :: 4 - Beta
Classifier: Environment :: Console
Classifier: Intended Audience :: Developers
Classifier: License :: OSI Approved :: BSD License
Classifier: Natural Language :: English
Classifier: Topic :: System :: Software Distribution
Classifier: Topic :: Utilities
Classifier: Topic :: Software Development :: Build Tools
Classifier: Topic :: Software Development :: Libraries :: Python Modules
Classifier: Programming Language :: Python :: 2
Classifier: Programming Language :: Python :: 3
